{"nodes": [{"id": "d_mca_project_ids_final_backend_app_core_security_py", "label": "security.py", "file_type": "code", "source_file": "D:\\MCA Project\\ids-final\\backend\\app\\core\\security.py", "source_location": "L1"}, {"id": "security_tokenscope", "label": "TokenScope", "file_type": "code", "source_file": "D:\\MCA Project\\ids-final\\backend\\app\\core\\security.py", "source_location": "L14"}, {"id": "str", "label": "str", "file_type": "code", "source_file": "", "source_location": ""}, {"id": "enum", "label": "Enum", "file_type": "code", "source_file": "", "source_location": ""}, {"id": "security_verifiedtoken", "label": "VerifiedToken", "file_type": "code", "source_file": "D:\\MCA Project\\ids-final\\backend\\app\\core\\security.py", "source_location": "L23"}, {"id": "security_verifiedtoken_init", "label": ".__init__()", "file_type": "code", "source_file": "D:\\MCA Project\\ids-final\\backend\\app\\core\\security.py", "source_location": "L25"}, {"id": "security_verifiedtoken_has_permission", "label": ".has_permission()", "file_type": "code", "source_file": "D:\\MCA Project\\ids-final\\backend\\app\\core\\security.py", "source_location": "L30"}, {"id": "security_verify_api_key", "label": "verify_api_key()", "file_type": "code", "source_file": "D:\\MCA Project\\ids-final\\backend\\app\\core\\security.py", "source_location": "L38"}, {"id": "security_require_scope", "label": "require_scope()", "file_type": "code", "source_file": "D:\\MCA Project\\ids-final\\backend\\app\\core\\security.py", "source_location": "L69"}, {"id": "security_rationale_15", "label": "Token permission scopes", "file_type": "rationale", "source_file": "D:\\MCA Project\\ids-final\\backend\\app\\core\\security.py", "source_location": "L15"}, {"id": "security_rationale_24", "label": "Token details after verification", "file_type": "rationale", "source_file": "D:\\MCA Project\\ids-final\\backend\\app\\core\\security.py", "source_location": "L24"}, {"id": "security_rationale_31", "label": "Check if token has required permission", "file_type": "rationale", "source_file": "D:\\MCA Project\\ids-final\\backend\\app\\core\\security.py", "source_location": "L31"}, {"id": "security_rationale_42", "label": "Dependency: validates X-API-Key header and returns token info.     Supports both", "file_type": "rationale", "source_file": "D:\\MCA Project\\ids-final\\backend\\app\\core\\security.py", "source_location": "L42"}, {"id": "security_rationale_70", "label": "Dependency to enforce token scope on specific endpoints", "file_type": "rationale", "source_file": "D:\\MCA Project\\ids-final\\backend\\app\\core\\security.py", "source_location": "L70"}], "edges": [{"source": "d_mca_project_ids_final_backend_app_core_security_py", "target": "enum", "relation": "imports_from", "confidence": "EXTRACTED", "source_file": "D:\\MCA Project\\ids-final\\backend\\app\\core\\security.py", "source_location": "L3", "weight": 1.0}, {"source": "d_mca_project_ids_final_backend_app_core_security_py", "target": "typing", "relation": "imports_from", "confidence": "EXTRACTED", "source_file": "D:\\MCA Project\\ids-final\\backend\\app\\core\\security.py", "source_location": "L4", "weight": 1.0}, {"source": "d_mca_project_ids_final_backend_app_core_security_py", "target": "fastapi", "relation": "imports_from", "confidence": "EXTRACTED", "source_file": "D:\\MCA Project\\ids-final\\backend\\app\\core\\security.py", "source_location": "L6", "weight": 1.0}, {"source": "d_mca_project_ids_final_backend_app_core_security_py", "target": "fastapi_security", "relation": "imports_from", "confidence": "EXTRACTED", "source_file": "D:\\MCA Project\\ids-final\\backend\\app\\core\\security.py", "source_location": "L7", "weight": 1.0}, {"source": "d_mca_project_ids_final_backend_app_core_security_py", "target": "app_core_config", "relation": "imports_from", "confidence": "EXTRACTED", "source_file": "D:\\MCA Project\\ids-final\\backend\\app\\core\\security.py", "source_location": "L9", "weight": 1.0}, {"source": "d_mca_project_ids_final_backend_app_core_security_py", "target": "security_tokenscope", "relation": "contains", "confidence": "EXTRACTED", "source_file": "D:\\MCA Project\\ids-final\\backend\\app\\core\\security.py", "source_location": "L14", "weight": 1.0}, {"source": "security_tokenscope", "target": "str", "relation": "inherits", "confidence": "EXTRACTED", "source_file": "D:\\MCA Project\\ids-final\\backend\\app\\core\\security.py", "source_location": "L14", "weight": 1.0}, {"source": "security_tokenscope", "target": "enum", "relation": "inherits", "confidence": "EXTRACTED", "source_file": "D:\\MCA Project\\ids-final\\backend\\app\\core\\security.py", "source_location": "L14", "weight": 1.0}, {"source": "d_mca_project_ids_final_backend_app_core_security_py", "target": "security_verifiedtoken", "relation": "contains", "confidence": "EXTRACTED", "source_file": "D:\\MCA Project\\ids-final\\backend\\app\\core\\security.py", "source_location": "L23", "weight": 1.0}, {"source": "security_verifiedtoken", "target": "security_verifiedtoken_init", "relation": "method", "confidence": "EXTRACTED", "source_file": "D:\\MCA Project\\ids-final\\backend\\app\\core\\security.py", "source_location": "L25", "weight": 1.0}, {"source": "security_verifiedtoken", "target": "security_verifiedtoken_has_permission", "relation": "method", "confidence": "EXTRACTED", "source_file": "D:\\MCA Project\\ids-final\\backend\\app\\core\\security.py", "source_location": "L30", "weight": 1.0}, {"source": "d_mca_project_ids_final_backend_app_core_security_py", "target": "security_verify_api_key", "relation": "contains", "confidence": "EXTRACTED", "source_file": "D:\\MCA Project\\ids-final\\backend\\app\\core\\security.py", "source_location": "L38", "weight": 1.0}, {"source": "d_mca_project_ids_final_backend_app_core_security_py", "target": "security_require_scope", "relation": "contains", "confidence": "EXTRACTED", "source_file": "D:\\MCA Project\\ids-final\\backend\\app\\core\\security.py", "source_location": "L69", "weight": 1.0}, {"source": "security_verify_api_key", "target": "security_verifiedtoken", "relation": "calls", "confidence": "EXTRACTED", "source_file": "D:\\MCA Project\\ids-final\\backend\\app\\core\\security.py", "source_location": "L56", "weight": 1.0}, {"source": "security_rationale_15", "target": "security_tokenscope", "relation": "rationale_for", "confidence": "EXTRACTED", "source_file": "D:\\MCA Project\\ids-final\\backend\\app\\core\\security.py", "source_location": "L15", "weight": 1.0}, {"source": "security_rationale_24", "target": "security_verifiedtoken", "relation": "rationale_for", "confidence": "EXTRACTED", "source_file": "D:\\MCA Project\\ids-final\\backend\\app\\core\\security.py", "source_location": "L24", "weight": 1.0}, {"source": "security_rationale_31", "target": "security_verifiedtoken_has_permission", "relation": "rationale_for", "confidence": "EXTRACTED", "source_file": "D:\\MCA Project\\ids-final\\backend\\app\\core\\security.py", "source_location": "L31", "weight": 1.0}, {"source": "security_rationale_42", "target": "security_verify_api_key", "relation": "rationale_for", "confidence": "EXTRACTED", "source_file": "D:\\MCA Project\\ids-final\\backend\\app\\core\\security.py", "source_location": "L42", "weight": 1.0}, {"source": "security_rationale_70", "target": "security_require_scope", "relation": "rationale_for", "confidence": "EXTRACTED", "source_file": "D:\\MCA Project\\ids-final\\backend\\app\\core\\security.py", "source_location": "L70", "weight": 1.0}], "raw_calls": [{"caller_nid": "security_verify_api_key", "callee": "HTTPException", "source_file": "D:\\MCA Project\\ids-final\\backend\\app\\core\\security.py", "source_location": "L47"}, {"caller_nid": "security_verify_api_key", "callee": "HTTPException", "source_file": "D:\\MCA Project\\ids-final\\backend\\app\\core\\security.py", "source_location": "L63"}]}